httpie_image.py
setup.py
httpie_image.egg-info/PKG-INFO
httpie_image.egg-info/SOURCES.txt
httpie_image.egg-info/dependency_links.txt
httpie_image.egg-info/entry_points.txt
httpie_image.egg-info/requires.txt
httpie_image.egg-info/top_level.txt