Metadata-Version: 1.0
Name: httpie-image
Version: 1.0.0
Summary: iTerm2 image display plugin for HTTPie.
Home-page: https://github.com/banteg/httpie-image
Author: banteg
Author-email: UNKNOWN
License: UNKNOWN
Platform: UNKNOWN
